{"statement":{"language":"es","images":[],"sources":[],"markdown":"# Descripci\u00f3n\nCalcula el \u00e1rea de $N$ c\u00edrculos, a partir de la longitud del radio de cada c\u00edrculo. Puede utilizar el valor de $\\pi$ como $3.1416$.\n\n# Entrada\nUn entero $N$ entre $1$ y $100$ (la cantidad de c\u00edrculos), y en la siguiente l\u00ednea $N$ racionales separados por espacios, cada uno representa la longitud del radio de un c\u00edrculo y tendr\u00e1 un valor entre $0$ y $1\\ 000$.\n\n# Salida\nSon $N$ racionales separados por un espacio, correspondientes al \u00e1rea de cada uno de los c\u00edrculos. Los valores calculados deben ser razonablemente cercanos a la respuesta exacta.\n\n# Ejemplo\n||input\n3\n0.5 3.3 1.2\n||output\n0.7854 34.212024 4.523904\n||end\n"},"settings":{"cases":{"statement_001":{"in":"3\n0.5 3.3 1.2","out":"0.7854 34.212024 4.523904","weight":1}},"limits":{"ExtraWallTime":"0s","MemoryLimit":33554432,"OutputLimit":10240,"OverallWallTimeLimit":"1m0s","TimeLimit":"1s"},"validator":{"name":"custom","tolerance":1.0e-9,"custom_validator":{"source":"","language":"cpp","limits":{"ExtraWallTime":"0s","MemoryLimit":268435456,"OutputLimit":10240,"OverallWallTimeLimit":"5s","TimeLimit":"1s"}}}},"problem_id":12741,"title":"\u00c1rea de N c\u00edrculos","alias":"areaNcirculos","input_limit":10240,"visits":0,"submissions":231,"accepted":60,"difficulty":0.5510687394705337,"creation_date":1612475403,"source":"UAM Azcapotzalco 2021","order":"normal","visibility":2,"email_clarifications":false,"allow_user_add_tags":false,"show_diff":"none","quality_seal":false,"version":"81b17fa770669a6d728240a40278650d9c88c41e","commit":"3eacbdb98d15d6c7c5de4a30371da54d904d0d45","nominationStatus":{"alreadyReviewed":false,"dismissed":false,"dismissedBeforeAc":false,"nominated":false,"nominatedBeforeAc":false,"language":"","canNominateProblem":false,"solved":false,"tried":false},"problemsetter":{"username":"mheredia","classname":"user-rank-expert","name":"Marco Heredia","creation_date":1612475403},"languages":["c11-gcc","c11-clang","cpp11-gcc","cpp11-clang","cpp17-gcc","cpp17-clang","java","py2","py3","rb","cs","pas","hs","lua"],"accepts_submissions":true,"karel_problem":false,"limits":{"input_limit":"10 KiB","memory_limit":"32 MiB","overall_wall_time_limit":"1m0s","time_limit":"1s"},"points":16.86,"score":0,"status":"ok","_id":"6186d3a7802af993684003"}