{"statement":{"language":"es","images":[],"sources":[],"markdown":"# Descripci\u00f3n\nHab\u00eda una vez una casa infestada de ratones. Un gato escuch\u00f3 hablar de ella y decidi\u00f3 vivir ah\u00ed, atrapando a los ratones uno tras otro. Un d\u00eda, los ratones no pudieron soportarlo m\u00e1s y todos corrieron al mismo tiempo hacia sus madrigueras para esconderse y permanecer ah\u00ed. Escribe un programa que, dadas las posiciones y vol\u00famenes de los ratones as\u00ed como las posiciones y capacidades de las madrigueras, calcule la cantidad m\u00ednima de segundos que se requiere para que todos los ratones logren esconderse.\n\n# Entrada\nUn entero $N$ seguido de $N$ parejas $R, V$ que denotan la posici\u00f3n y el volumen de cada uno de los $N$ ratones. Posteriormente un entero $M$ seguido de $M$ parejas $P, C$ que denotan la posici\u00f3n y la capacidad de cada una de las $M$ madrigueras. Puedes suponer que $1 \\leq N,M \\leq 20$, $0 \\leq R,P \\leq 100$, $1 \\leq V,C \\leq 6$, que todas las posiciones (ratones y madrigueras) son distintas y que los ratones corren a una velocidad de una posici\u00f3n por segundo.\n\n# Salida\nUn entero que sea la cantidad m\u00ednima de segundos requerida para que los ratones logren esconderse o el entero $-1$ si no existe soluci\u00f3n.\n\n# Ejemplo\n||input\n2\n3 4\n5 3\n2\n1 3\n8 5\n||output\n5\n||description\nEl primer rat\u00f3n debe ir a la segunda madriguera (y le toma 5 segundos).\n\nEl segundo rat\u00f3n debe ir a la primera madriguera (y le toma 4 segundos).\n\nComo los ratones corren al mismo tiempo, el tiempo m\u00ednimo requerido es de 5 segundos.\n||input\n2\n3 3\n5 3\n2\n6 3\n4 2\n||output\n-1\n||description\nNo hay manera de que ambos ratones puedan esconderse.\n||end\n"},"settings":{"cases":{"statement_001":{"in":"2\n3 4\n5 3\n2\n1 3\n8 5","out":"5","weight":1},"statement_002":{"in":"2\n3 3\n5 3\n2\n6 3\n4 2","out":"-1","weight":1}},"limits":{"ExtraWallTime":"0s","MemoryLimit":33554432,"OutputLimit":16384,"OverallWallTimeLimit":"1m0s","TimeLimit":"1s"},"validator":{"name":"token-caseless","group_score_policy":"sum-if-not-zero"}},"problem_id":5067,"title":"El gato y los ratones","alias":"El-gato-y-los-ratones","input_limit":10240,"visits":0,"submissions":320,"accepted":9,"difficulty":1.577088899874225,"creation_date":1487438284,"source":"UAM Azcapotzalco 2017","order":"normal","visibility":2,"email_clarifications":false,"allow_user_add_tags":false,"show_diff":"none","quality_seal":true,"version":"591a9fb1bf66e8b328e0eba3c1cc8e7eebb035db","commit":"afddebba098b954f2272bf54250f52f1d79ab134","nominationStatus":{"alreadyReviewed":false,"dismissed":false,"dismissedBeforeAc":false,"nominated":false,"nominatedBeforeAc":false,"language":"","canNominateProblem":false,"solved":false,"tried":false},"problemsetter":{"username":"rcc","classname":"user-rank-international-master","name":"rcc","creation_date":1487438284},"languages":["c11-gcc","c11-clang","cpp11-gcc","cpp11-clang","cpp17-gcc","cpp17-clang","java","py2","py3","rb","cs","pas","hs","lua"],"accepts_submissions":true,"karel_problem":false,"limits":{"input_limit":"10 KiB","memory_limit":"32 MiB","overall_wall_time_limit":"1m0s","time_limit":"1s"},"points":30.1,"score":0,"status":"ok","_id":"6186d3997dcfb791870259"}