{"statement":{"language":"es","images":[],"sources":[],"markdown":"# Descripci\u00f3n\nEres un famoso vidente y has decidido incursionar en el mundo del golf para obtener m\u00e1s dinero. Aunque quieres aprovechar tus poderes para obtener un mejor desempe\u00f1o, pronto te diste cuenta que conocer el futuro no te convierte un buen golfista: en tu visi\u00f3n del futuro puedes ver la distancia que recorrer\u00e1 la bola en cada uno de tus siguientes $N$ tiros, pero no puedes cambiar las distancias ni el orden en el que ocurrir\u00e1n. El campo de golf es un plano en dos dimensiones y lo que s\u00ed puedes elegir sin restricciones  es la orientaci\u00f3n de cada tiro. Para al menos dar la batalla en el pr\u00f3ximo torneo, deseas escribir un programa que determine si ser\u00e1 posible llevar la bola de golf de su punto inicial al agujero de meta usando los tiros de tu visi\u00f3n.\n\n# Entrada\nCuatro enteros $X_1, Y_1, X_2, Y_2$ que denotan la posici\u00f3n inicial de la bola y la posici\u00f3n de la meta, respectivamente. Posteriormente, un entero $N$ seguido de $N$ enteros $D_1, D_2, \\dots, D_N$ que denotan la magnitud de la distancia de tus $N$ tiros. Puedes suponer que $-10^5 \\leq X_1, Y_1, X_2, Y_2 \\leq +10^5$, que $1 \\leq D_i \\leq 10^6$ y que $D_1 + D_2 + \\dots + D_N \\leq 10^9$.\n\n# Salida\nUn entero que sea la menor cantidad de tiros que necesitas para llevar la bola de golf a la meta o el entero $-1$ si es imposible.\n\n# Ejemplo\n||input\n1 2 5 5\n2\n5 1\n||output\n1\n||input\n1 2 5 5\n2\n1 5\n||output\n2\n||input\n1 2 5 5\n2\n10 50\n||output\n-1\n||end\n"},"settings":{"cases":{"statement_001":{"in":"1 2 5 5\n2\n5 1","out":"1","weight":1},"statement_002":{"in":"1 2 5 5\n2\n1 5","out":"2","weight":1},"statement_003":{"in":"1 2 5 5\n2\n10 50","out":"-1","weight":1}},"limits":{"ExtraWallTime":"0s","MemoryLimit":33554432,"OutputLimit":10240,"OverallWallTimeLimit":"1m0s","TimeLimit":"500ms"},"validator":{"name":"token","tolerance":1.0e-9}},"problem_id":10860,"title":"El golfista vidente","alias":"El-golfista-vidente","input_limit":10240,"visits":0,"submissions":19,"accepted":0,"difficulty":null,"creation_date":1587661452,"source":"UAM Azcapotzalco 2020","order":"normal","visibility":2,"email_clarifications":false,"allow_user_add_tags":false,"show_diff":"none","quality_seal":true,"version":"94b6002e3d74faa015c9a67a9b01412d39dd65ad","commit":"4f1ca45fc6e6d5f43dd1ed5f44b6470421fe6008","nominationStatus":{"alreadyReviewed":false,"dismissed":false,"dismissedBeforeAc":false,"nominated":false,"nominatedBeforeAc":false,"language":"","canNominateProblem":false,"solved":false,"tried":false},"problemsetter":{"username":"rcc","classname":"user-rank-international-master","name":"rcc","creation_date":1587661452},"languages":["c11-gcc","c11-clang","cpp11-gcc","cpp11-clang","cpp17-gcc","cpp17-clang","java","py2","py3","rb","cs","pas","hs","lua"],"accepts_submissions":true,"karel_problem":false,"limits":{"input_limit":"10 KiB","memory_limit":"32 MiB","overall_wall_time_limit":"1m0s","time_limit":"500ms"},"points":100,"score":0,"status":"ok","_id":"6186d39edd921986708018"}