{"statement":{"language":"es","images":[],"sources":[],"markdown":"# Descripci\u00f3n\nEscribe un programa que, dados los valores de las inc\u00f3gnitas $x_0, x_1, \\dots, x_{n-1}$, eval\u00fae una secuencia de polinomios. Cada polinomio es una suma de productos de variables.\n\n# Entrada\nEl entero $N$ seguido de $N$ n\u00fameros en punto flotante, Posteriormente una secuencia de polinomios, uno por l\u00ednea, los cuales deben procesarse hasta el fin de archivo. Puedes suponer que $1 \\leq N \\leq 10$.\n\n# Salida\nPor cada polinomio, un real que corresponda con la evaluaci\u00f3n del polinomio. El valor impreso se considerar\u00e1 correcto si est\u00e1 razonablemente cerca del valor exacto.\n\n# Ejemplo\n\n||input\n3\n3.14 2.71 1.414\nx0x1 + x2\nx2 + x0 + x1\nx0x1x2\n||output\n9.92\n7.26\n12.03\n||end\n"},"settings":{"cases":{"statement_001":{"in":"3\n3.14 2.71 1.414\nx0x1 + x2\nx2 + x0 + x1\nx0x1x2","out":"9.92\n7.26\n12.03","weight":1}},"limits":{"ExtraWallTime":"0s","MemoryLimit":33554432,"OutputLimit":32768,"OverallWallTimeLimit":"1m0s","TimeLimit":"1s"},"validator":{"name":"custom","custom_validator":{"source":"","language":"cpp"}}},"problem_id":2981,"title":"Evaluar polinomios","alias":"Evaluar-polinomios","input_limit":10240,"visits":0,"submissions":55,"accepted":9,"difficulty":1.3043616271469523,"creation_date":1442958505,"source":"UAM Azcapotzalco","order":"normal","visibility":2,"email_clarifications":false,"allow_user_add_tags":false,"show_diff":"none","quality_seal":true,"version":"b6b5e92e6c00595ba545f6eba5dd9d030841c8d8","commit":"a322dd57a018b5faa9357a290412af55ca4c8f05","nominationStatus":{"alreadyReviewed":false,"dismissed":false,"dismissedBeforeAc":false,"nominated":false,"nominatedBeforeAc":false,"language":"","canNominateProblem":false,"solved":false,"tried":false},"problemsetter":{"username":"rcc","classname":"user-rank-international-master","name":"rcc","creation_date":1442958505},"languages":["c11-gcc","c11-clang","cpp11-gcc","cpp11-clang","cpp17-gcc","cpp17-clang","java","py2","py3","rb","cs","pas","hs","lua"],"accepts_submissions":true,"karel_problem":false,"limits":{"input_limit":"10 KiB","memory_limit":"32 MiB","overall_wall_time_limit":"1m0s","time_limit":"1s"},"points":30.1,"score":0,"status":"ok","_id":"6186d3983d287869452078"}