{"statement":{"language":"es","images":[],"sources":[],"markdown":"# Descripci\u00f3n\n\nSeguramente ya sabes c\u00f3mo encontrar el camino m\u00e1s corto para escapar de un laberinto, pero lamentablemente esta vez tu misi\u00f3n es mucho m\u00e1s peligrosa pues ciertos lugares de \u00e9ste est\u00e1n\nocupados por lobos que intentar\u00e1n comerte. Como est\u00e1s en forma, crees poder enfrentarte con $L$ lobos pero probablemente el lobo $L$ + 1 ya sea demasiado para ti. Tu labor ser\u00e1 encontrar la ruta m\u00e1s corta para escapar del laberinto evitando enfrentarte con m\u00e1s de $L$ lobos durante tu recorrido.\n\n# Entrada\n\nEl valor del entero $L$ seguido de un entero $N$ y de un tablero de $N$ \u00d7 $N$ caracteres. Una $E$ y una $S$ representan la entrada y la salida del laberinto respectivamente mientras que un $#$ representa un muro, un $*$ representa un lobo y un $.$ la ausencia de obst\u00e1culos. Puedes suponer que $L$ &ge; 0, 2 &le; $N$ &le; 100 y que existir\u00e1n exactamente una entrada y una salida.\n\n# Salida\n\nUn entero $P$ que sea el menor n\u00famero de pasos usados para salir del laberinto sin enfrentar m\u00e1s de $L$ lobos o -1 si no existe soluci\u00f3n.\n\n# Ejemplo\n\n||input\n1\n6\n######\n#*S..#\n#*##.#\n#.##*#\nE....#\n######\n||output\n9\n||end\n"},"settings":{"cases":{"statement_001":{"in":"1\n6\n######\n#*S..#\n#*##.#\n#.##*#\nE....#\n######","out":"9","weight":1}},"limits":{"ExtraWallTime":"0s","MemoryLimit":33554432,"OutputLimit":16384,"OverallWallTimeLimit":"1m0s","TimeLimit":"1s"},"validator":{"name":"token-caseless"}},"problem_id":2816,"title":"Laberinto salvajemente peligroso","alias":"lsp","input_limit":10240,"visits":0,"submissions":191,"accepted":23,"difficulty":2.5385792192655794,"creation_date":1433427540,"source":"UAM Azcapotzalco 2011","order":"normal","visibility":2,"email_clarifications":false,"allow_user_add_tags":false,"show_diff":"none","quality_seal":true,"version":"8dd16bce2ce0c2896d1ee7510f8d5b73cf88d24d","commit":"21888baf74cc7fc1d2012ca97fdac1cfee8bdb21","nominationStatus":{"alreadyReviewed":false,"dismissed":false,"dismissedBeforeAc":false,"nominated":false,"nominatedBeforeAc":false,"language":"","canNominateProblem":false,"solved":false,"tried":false},"problemsetter":{"username":"rcc","classname":"user-rank-international-master","name":"rcc","creation_date":1433427540},"languages":["c11-gcc","c11-clang","cpp11-gcc","cpp11-clang","cpp17-gcc","cpp17-clang","java","py2","py3","rb","cs","pas","hs","lua"],"accepts_submissions":true,"karel_problem":false,"limits":{"input_limit":"10 KiB","memory_limit":"32 MiB","overall_wall_time_limit":"1m0s","time_limit":"1s"},"points":21.81,"score":0,"status":"ok","_id":"6186d3983b58d439892199"}