{"statement":{"language":"es","images":[],"sources":[],"markdown":"# Descripci\u00f3n\nDadas dos cadenas, escribe un programa que calcule su subsecuencia com\u00fan m\u00e1s larga. Una subsecuencia com\u00fan se define como una selecci\u00f3n de posiciones en ambas cadenas donde los caracteres de una y otra son iguales y adem\u00e1s se respeta el orden de aparici\u00f3n de los mismos en las cadenas. Una posici\u00f3n de una cadena no se puede hacer coincidir con m\u00e1s de una posici\u00f3n de la otra cadena.\n\n# Entrada\nDos cadenas $S$ y $T$. Puedes suponer que las cadenas est\u00e1n formadas \u00fanicamente por letras y que tienen una longitud m\u00e1xima de $45000$ caracteres.\n\n# Salida\nUn entero $N$ que sea la longitud de la subsecuencia com\u00fan m\u00e1s larga de $S$ y $T$. Si ninguna cadena supera los $1000$ caracteres de longitud, tambi\u00e9n deber\u00e1n imprimirse $N$ parejas de enteros $I_S, J_T$ que denotan las posiciones de las coincidencias que conforman la subsecuencia (en orden). Si hay m\u00e1s de una respuesta, puedes imprimir cualquiera de ellas.\n\n# Ejemplo\n||input\ngatito\natetogg\n||output\n4\n1 0\n2 1\n4 3\n5 4\n||end\n"},"settings":{"cases":{"statement_001":{"in":"gatito\natetogg","out":"4\n1 0\n2 1\n4 3\n5 4","weight":1}},"limits":{"ExtraWallTime":"0s","MemoryLimit":33554432,"OutputLimit":10240,"OverallWallTimeLimit":"1m0s","TimeLimit":"5s"},"validator":{"name":"custom","tolerance":1.0e-9,"custom_validator":{"source":"","language":"cpp","limits":{"ExtraWallTime":"0s","MemoryLimit":268435456,"OutputLimit":10240,"OverallWallTimeLimit":"5s","TimeLimit":"5s"}}}},"problem_id":8618,"title":"Subsecuencia com\u00fan m\u00e1s larga","alias":"Subsecuencia-comun-mas-larga","input_limit":10240,"visits":0,"submissions":117,"accepted":21,"difficulty":1.8344598383551134,"creation_date":1561605472,"source":"UAM Azcapotzalco 2019","order":"normal","visibility":2,"email_clarifications":false,"allow_user_add_tags":true,"show_diff":"none","quality_seal":true,"version":"c4fc040cfa3ef8413432153867fc90422af031ae","commit":"48fba27f115f7f148eaa4c550739fa4832066a18","nominationStatus":{"alreadyReviewed":false,"dismissed":false,"dismissedBeforeAc":false,"nominated":false,"nominatedBeforeAc":false,"language":"","canNominateProblem":false,"solved":false,"tried":false},"problemsetter":{"username":"rcc","classname":"user-rank-international-master","name":"rcc","creation_date":1561605472},"languages":["c11-gcc","c11-clang","cpp11-gcc","cpp11-clang","cpp17-gcc","cpp17-clang","java","py2","py3","rb","cs","pas","hs","lua"],"accepts_submissions":true,"karel_problem":false,"limits":{"input_limit":"10 KiB","memory_limit":"32 MiB","overall_wall_time_limit":"1m0s","time_limit":"5s"},"points":22.42,"score":0,"status":"ok","_id":"6186d39ddf4f0716837808"}